openapi2mcpserver/__init__.py
openapi2mcpserver/app_config.py
openapi2mcpserver/core.py
openapi2mcpserver-0.1.3.dist-info/METADATA
openapi2mcpserver-0.1.3.dist-info/WHEEL
openapi2mcpserver-0.1.3.dist-info/entry_points.txt
openapi2mcpserver-0.1.3.dist-info/top_level.txt
openapi2mcpserver-0.1.3.dist-info/RECORD
