Metadata-Version: 2.4
Name: openapi2mcpserver
Version: 0.1.3
Summary: OpenAPI to MCP服务器，提供OpenAPI转换为MCP功能
Author-email: Jewei <jiweifong@qq.com>
Project-URL: Homepage, https://github.com/jeweis/openapi2mcpserver
Project-URL: Bug Tracker, https://github.com/jeweis/openapi2mcpserver/issues
Classifier: Programming Language :: Python :: 3
Classifier: License :: OSI Approved :: MIT License
Classifier: Operating System :: OS Independent
Requires-Python: >=3.10
Requires-Dist: fastmcp>=0.1.0
Requires-Dist: python-dotenv>=0.19.0
Requires-Dist: httpx>=0.24.0
